qiskit_iqm/__init__.py
qiskit_iqm/iqm_backend.py
qiskit_iqm/iqm_job.py
qiskit_iqm/iqm_provider.py
qiskit_iqm/py.typed
qiskit_iqm/qiskit_to_iqm.py
qiskit_iqm/fake_backends/__init__.py
qiskit_iqm/fake_backends/fake_adonis.py
qiskit_iqm/fake_backends/iqm_fake_backend.py
qiskit_iqm_unstable-10.5.dist-info/AUTHORS.rst
qiskit_iqm_unstable-10.5.dist-info/LICENSE
qiskit_iqm_unstable-10.5.dist-info/METADATA
qiskit_iqm_unstable-10.5.dist-info/WHEEL
qiskit_iqm_unstable-10.5.dist-info/top_level.txt
qiskit_iqm_unstable-10.5.dist-info/RECORD
