Metadata-Version: 2.1
Name: qiskit-iqm-unstable
Version: 10.5
Summary: Qiskit adapter for IQM's quantum architectures
Author-email: IQM Finland Oy <developers@meetiqm.com>
License: Apache License
Project-URL: homepage, https://github.com/iqm-finland/qiskit-on-iqm
Project-URL: documentation, https://iqm-finland.github.io/qiskit-on-iqm
Project-URL: repository, https://github.com/iqm-finland/qiskit-on-iqm.git
Project-URL: changelog, https://github.com/iqm-finland/qiskit-on-iqm/blob/main/CHANGELOG.rst
Classifier: Development Status :: 4 - Beta
Classifier: Programming Language :: Python :: 3 :: Only
Classifier: Topic :: Scientific/Engineering :: Physics
Classifier: Intended Audience :: Science/Research
Classifier: License :: OSI Approved :: Apache Software License
Requires-Python: <3.12,>=3.9
License-File: LICENSE
License-File: AUTHORS.rst
Requires-Dist: numpy
Requires-Dist: qiskit (~=0.42.1)
Requires-Dist: iqm-client (<14.0,>=13.0)
Provides-Extra: cicd
Requires-Dist: twine (<4.0,>=3.8.0) ; extra == 'cicd'
Provides-Extra: dev
Requires-Dist: tox (==3.26.0) ; extra == 'dev'
Provides-Extra: docs
Requires-Dist: sphinx (==4.5.0) ; extra == 'docs'
Requires-Dist: sphinx-book-theme (==0.3.3) ; extra == 'docs'
Requires-Dist: sphinx-multiversion-contrib (==0.2.12) ; extra == 'docs'
Provides-Extra: testing
Requires-Dist: black (==22.10.0) ; extra == 'testing'
Requires-Dist: isort (==5.10.1) ; extra == 'testing'
Requires-Dist: mockito (==1.3.0) ; extra == 'testing'
Requires-Dist: mypy (==0.982) ; extra == 'testing'
Requires-Dist: pytest (==7.0.1) ; extra == 'testing'
Requires-Dist: pytest-cov (==3.0.0) ; extra == 'testing'
Requires-Dist: pytest-isort (==3.0.0) ; extra == 'testing'
Requires-Dist: pytest-mypy (==0.9.1) ; extra == 'testing'
Requires-Dist: pytest-pylint (==0.18.0) ; extra == 'testing'
Requires-Dist: types-Jinja2 (==2.11.9) ; extra == 'testing'
